tborg/__init__.py
tborg/tborg.py
python_thunderborg-1.0.2.dist-info/LICENSE.md
python_thunderborg-1.0.2.dist-info/METADATA
python_thunderborg-1.0.2.dist-info/WHEEL
python_thunderborg-1.0.2.dist-info/top_level.txt
python_thunderborg-1.0.2.dist-info/RECORD
