Metadata-Version: 2.1
Name: python-thunderborg
Version: 1.0.2
Summary: ThunderBorg Motor Controller API
Home-page: https://github.com/cnobile2012/python-thunderborg
Author: Carl J. Nobile
Author-email: carl.nobile@gmail.com
License: MIT
Classifier: Environment :: Web Environment
Classifier: Intended Audience :: Developers
Classifier: License :: OSI Approved :: MIT License
Classifier: Operating System :: OS Independent
Classifier: Programming Language :: Python
Classifier: Programming Language :: Python :: 2
Classifier: Programming Language :: Python :: 2.7
Classifier: Programming Language :: Python :: 3
Classifier: Programming Language :: Python :: 3.8
Classifier: Programming Language :: Python :: 3.9
Classifier: Topic :: Internet :: WWW/HTTP
Classifier: Topic :: Internet :: WWW/HTTP :: Dynamic Content
License-File: LICENSE.md
Requires-Dist: six
